llama_index/llms/dashscope/__init__.py
llama_index/llms/dashscope/base.py
llama_index/llms/dashscope/utils.py
llama_index_llms_dashscope-0.5.2.dist-info/METADATA
llama_index_llms_dashscope-0.5.2.dist-info/WHEEL
llama_index_llms_dashscope-0.5.2.dist-info/licenses/LICENSE
llama_index_llms_dashscope-0.5.2.dist-info/RECORD
